kap/__init__.py
kap/_types.py
kap/_version.py
kap/assignment.py
kap-0.2.1.dist-info/LICENSE.txt
kap-0.2.1.dist-info/METADATA
kap-0.2.1.dist-info/WHEEL
kap-0.2.1.dist-info/top_level.txt
kap-0.2.1.dist-info/RECORD
