Metadata-Version: 2.1
Name: kap
Version: 0.2.1
Summary: Gabrovšek's Multiple Hungarian method for solving k-Assignment Problem.
Home-page: https://github.com/inspiros/kap
Author: Hoang-Nhat Tran (inspiros)
Author-email: hnhat.tran@gmail.com
License: MIT
Project-URL: Source, https://github.com/inspiros/kap
Keywords: k-assignment,k-partite-matching,linear-assignment,bi-partite-matching,hungarian
Classifier: Development Status :: 3 - Alpha
Classifier: Intended Audience :: Developers
Classifier: Intended Audience :: Education
Classifier: Intended Audience :: Science/Research
Classifier: License :: OSI Approved :: MIT License
Classifier: Programming Language :: Python
Classifier: Programming Language :: Python :: 3
Classifier: Programming Language :: Python :: 3.7
Classifier: Programming Language :: Python :: 3.8
Classifier: Programming Language :: Python :: 3.9
Classifier: Programming Language :: Python :: 3.10
Classifier: Programming Language :: Python :: 3.11
Classifier: Operating System :: OS Independent
Classifier: Topic :: Scientific/Engineering :: Mathematics
Requires-Python: >=3.7
License-File: LICENSE.txt
Requires-Dist: numpy
